cwyodmodules/__init__.py
cwyodmodules/mgmt_config.py
cwyodmodules/api/__init__.py
cwyodmodules/api/chat_history.py
cwyodmodules/batch/__init__.py
cwyodmodules/batch/utilities/__init__.py
cwyodmodules/batch/utilities/chat_history/auth_utils.py
cwyodmodules/batch/utilities/chat_history/database_client_base.py
cwyodmodules/batch/utilities/chat_history/database_factory.py
cwyodmodules/batch/utilities/chat_history/postgresdbservice.py
cwyodmodules/batch/utilities/chat_history/sample_user.py
cwyodmodules/batch/utilities/common/__init__.py
cwyodmodules/batch/utilities/common/answer.py
cwyodmodules/batch/utilities/common/source_document.py
cwyodmodules/batch/utilities/document_chunking/__init__.py
cwyodmodules/batch/utilities/document_chunking/chunking_strategy.py
cwyodmodules/batch/utilities/document_chunking/document_chunking_base.py
cwyodmodules/batch/utilities/document_chunking/fixed_size_overlap.py
cwyodmodules/batch/utilities/document_chunking/json.py
cwyodmodules/batch/utilities/document_chunking/layout.py
cwyodmodules/batch/utilities/document_chunking/page.py
cwyodmodules/batch/utilities/document_chunking/paragraph.py
cwyodmodules/batch/utilities/document_chunking/strategies.py
cwyodmodules/batch/utilities/document_loading/__init__.py
cwyodmodules/batch/utilities/document_loading/document_loading_base.py
cwyodmodules/batch/utilities/document_loading/layout.py
cwyodmodules/batch/utilities/document_loading/read.py
cwyodmodules/batch/utilities/document_loading/strategies.py
cwyodmodules/batch/utilities/document_loading/web.py
cwyodmodules/batch/utilities/document_loading/word_document.py
cwyodmodules/batch/utilities/helpers/__init__.py
cwyodmodules/batch/utilities/helpers/azure_form_recognizer_helper.py
cwyodmodules/batch/utilities/helpers/azure_postgres_helper.py
cwyodmodules/batch/utilities/helpers/document_chunking_helper.py
cwyodmodules/batch/utilities/helpers/document_loading_helper.py
cwyodmodules/batch/utilities/helpers/env_helper.py
cwyodmodules-0.9.52.dist-info/licenses/LICENSE
cwyodmodules-0.9.52.dist-info/METADATA
cwyodmodules-0.9.52.dist-info/WHEEL
cwyodmodules-0.9.52.dist-info/top_level.txt
cwyodmodules-0.9.52.dist-info/RECORD
