Metadata-Version: 2.4
Name: cwyodmodules
Version: 0.9.52
Summary: Add your description here
Author-email: Patrik <patrikhartl@gmail.com>
Classifier: Operating System :: OS Independent
Requires-Python: <3.12,>=3.11.10
License-File: LICENSE
Requires-Dist: openai==1.95.1
Requires-Dist: flask==3.1.1
Requires-Dist: azure-mgmt-cognitiveservices<14.0.0,>=13.6.0
Requires-Dist: asyncpg<0.31.0,>=0.30.0
Requires-Dist: chardet==5.2.0
Requires-Dist: azure-ai-formrecognizer<4.0.0,>=3.3.3
Requires-Dist: tiktoken<1.0.0,>=0.8.0
Requires-Dist: azure-functions==1.23.0
Requires-Dist: python-docx<2.0.0,>=1.1.2
Requires-Dist: azure-ai-contentsafety<2.0.0,>=1.0.0
Requires-Dist: httpx<0.29.0,>=0.28.1
Requires-Dist: requests<3.0.0,>=2.32.3
Requires-Dist: azure-cognitiveservices-speech<2.0.0,>=1.42.0
Requires-Dist: psycopg==3.2.4
Requires-Dist: psycopg2-binary==2.9.10
Requires-Dist: psycopg[binary]
Requires-Dist: beautifulsoup4==4.13.3
Requires-Dist: semantic-kernel==1.3.0
Requires-Dist: pydantic==2.7.4
Requires-Dist: pandas>=2.2.3
Requires-Dist: langchain==0.3.26
Requires-Dist: azpaddypy>=0.9.20
Dynamic: license-file
